toolformer_pytorch/__init__.py
toolformer_pytorch/optimizer.py
toolformer_pytorch/palm.py
toolformer_pytorch/prompts.py
toolformer_pytorch/toolformer_pytorch.py
toolformer_pytorch/tools.py
toolformer_pytorch-0.0.30.dist-info/LICENSE
toolformer_pytorch-0.0.30.dist-info/METADATA
toolformer_pytorch-0.0.30.dist-info/WHEEL
toolformer_pytorch-0.0.30.dist-info/top_level.txt
toolformer_pytorch-0.0.30.dist-info/RECORD
