Metadata-Version: 2.1
Name: toolformer-pytorch
Version: 0.0.30
Summary: Toolformer - Pytorch
Home-page: https://github.com/lucidrains/toolformer-pytorch
Author: Phil Wang
Author-email: lucidrains@gmail.com
License: MIT
Keywords: artificial intelligence,deep learning,transformers,attention mechanism,automated-tool-use
Classifier: Development Status :: 4 - Beta
Classifier: Intended Audience :: Developers
Classifier: Topic :: Scientific/Engineering :: Artificial Intelligence
Classifier: License :: OSI Approved :: MIT License
Classifier: Programming Language :: Python :: 3.6
License-File: LICENSE
Requires-Dist: beartype
Requires-Dist: einops >=0.4
Requires-Dist: torch >=1.6
Requires-Dist: tqdm
Requires-Dist: x-clip >=0.14.3
